dcimglib/__init__.py
dcimglib/api.py
dcimglib/core.py
dcimglib-0.0.1.dist-info/LICENSE
dcimglib-0.0.1.dist-info/METADATA
dcimglib-0.0.1.dist-info/WHEEL
dcimglib-0.0.1.dist-info/top_level.txt
dcimglib-0.0.1.dist-info/RECORD
